ldrb/__init__.py
ldrb/calculus.py
ldrb/ldrb.py
ldrb/save.py
ldrb/utils.py
ldrb-2025.0.1.dist-info/licenses/LICENSE
ldrb-2025.0.1.dist-info/METADATA
ldrb-2025.0.1.dist-info/WHEEL
ldrb-2025.0.1.dist-info/top_level.txt
ldrb-2025.0.1.dist-info/RECORD
