Metadata-Version: 2.4
Name: ldrb
Version: 2025.0.1
Summary: Laplace-Dirichlet Rule-based algorithm for assigning myocardial fiber orientations.
Home-page: https://github.com/finsberg/ldrb
Author: Henrik Finsberg
Author-email: henriknf@simula.no
License: LGPL-3.0
Keywords: cardiac modeling,fiber orientations
Classifier: Programming Language :: Python :: 3
Classifier: Programming Language :: Python :: 3 :: Only
Requires-Python: >=3.10
License-File: LICENSE
Requires-Dist: h5py
Requires-Dist: numba<0.58
Requires-Dist: numpy
Provides-Extra: dev
Requires-Dist: black; extra == "dev"
Requires-Dist: bump2version; extra == "dev"
Requires-Dist: flake8; extra == "dev"
Requires-Dist: ipython; extra == "dev"
Requires-Dist: isort; extra == "dev"
Requires-Dist: mypy; extra == "dev"
Requires-Dist: pdbpp; extra == "dev"
Requires-Dist: pip; extra == "dev"
Requires-Dist: pre-commit; extra == "dev"
Requires-Dist: sphinx; extra == "dev"
Requires-Dist: twine; extra == "dev"
Requires-Dist: wheel; extra == "dev"
Provides-Extra: docs
Requires-Dist: Sphinx; extra == "docs"
Requires-Dist: jupyter-book<2.0; extra == "docs"
Requires-Dist: jupytext; extra == "docs"
Requires-Dist: myst-parser; extra == "docs"
Requires-Dist: nbsphinx; extra == "docs"
Requires-Dist: pandoc; extra == "docs"
Provides-Extra: test
Requires-Dist: black; extra == "test"
Requires-Dist: cardiac-geometries; extra == "test"
Requires-Dist: flake8; extra == "test"
Requires-Dist: mypy; extra == "test"
Requires-Dist: pytest; extra == "test"
Requires-Dist: pytest-cov; extra == "test"
Dynamic: license-file
